huum_cli/__init__.py
huum_cli/cli.py
huum_cli/api/__init__.py
huum_cli/api/client.py
huum_cli/api/models.py
huum_cli/commands/__init__.py
huum_cli/commands/auth.py
huum_cli/commands/start.py
huum_cli/commands/statistics.py
huum_cli/commands/status.py
huum_cli/commands/stop.py
huum_cli/utils/__init__.py
huum_cli/utils/formatters.py
huum_cli/utils/plot.py
huum_cli/utils/storage.py
huum_cli/utils/validators.py
huum_cli-0.2.1.dist-info/METADATA
huum_cli-0.2.1.dist-info/WHEEL
huum_cli-0.2.1.dist-info/entry_points.txt
huum_cli-0.2.1.dist-info/licenses/LICENSE
huum_cli-0.2.1.dist-info/RECORD
