Metadata-Version: 2.4
Name: huum-cli
Version: 0.2.1
Summary: CLI for managing Huum sauna devices
Project-URL: Homepage, https://github.com/tomdyson/huum-cli
Project-URL: Repository, https://github.com/tomdyson/huum-cli
Project-URL: Issues, https://github.com/tomdyson/huum-cli/issues
Author-email: Tom Dyson <tom@torchbox.com>
License: MIT
License-File: LICENSE
Keywords: cli,huum,iot,sauna,smart-home
Classifier: Development Status :: 4 - Beta
Classifier: Environment :: Console
Classifier: Intended Audience :: End Users/Desktop
Classifier: License :: OSI Approved :: MIT License
Classifier: Operating System :: OS Independent
Classifier: Programming Language :: Python :: 3
Classifier: Programming Language :: Python :: 3.11
Classifier: Programming Language :: Python :: 3.12
Classifier: Topic :: Home Automation
Requires-Python: >=3.11
Requires-Dist: httpx>=0.25.0
Requires-Dist: keyring>=25.0.0
Requires-Dist: plotext>=5.2.8
Requires-Dist: pydantic>=2.0.0
Requires-Dist: rich>=13.0.0
Requires-Dist: tenacity>=8.2.0
Requires-Dist: typer>=0.9.0
Provides-Extra: dev
Requires-Dist: mypy>=1.7.0; extra == 'dev'
Requires-Dist: pytest-mock>=3.12.0; extra == 'dev'
Requires-Dist: pytest>=7.4.0; extra == 'dev'
Requires-Dist: ruff>=0.1.0; extra == 'dev'
